uvm/__init__.py
uvm/uvm_macros.py
uvm/uvm_pkg.py
uvm/uvm_unit.py
uvm/version.py
uvm/base/__init__.py
uvm/base/sv.py
uvm/base/uvm_barrier.py
uvm/base/uvm_bottomup_phase.py
uvm/base/uvm_callback.py
uvm/base/uvm_cmdline_processor.py
uvm/base/uvm_common_phases.py
uvm/base/uvm_comparer.py
uvm/base/uvm_component.py
uvm/base/uvm_config_db.py
uvm/base/uvm_coreservice.py
uvm/base/uvm_debug.py
uvm/base/uvm_domain.py
uvm/base/uvm_event.py
uvm/base/uvm_exceptions.py
uvm/base/uvm_factory.py
uvm/base/uvm_global_vars.py
uvm/base/uvm_globals.py
uvm/base/uvm_links.py
uvm/base/uvm_mailbox.py
uvm/base/uvm_misc.py
uvm/base/uvm_object.py
uvm/base/uvm_object_globals.py
uvm/base/uvm_objection.py
uvm/base/uvm_packer.py
uvm/base/uvm_phase.py
uvm/base/uvm_pool.py
uvm/base/uvm_port_base.py
uvm/base/uvm_printer.py
uvm/base/uvm_queue.py
uvm/base/uvm_recorder.py
uvm/base/uvm_registry.py
uvm/base/uvm_report_catcher.py
uvm/base/uvm_report_handler.py
uvm/base/uvm_report_message.py
uvm/base/uvm_report_object.py
uvm/base/uvm_report_server.py
uvm/base/uvm_resource.py
uvm/base/uvm_resource_db.py
uvm/base/uvm_root.py
uvm/base/uvm_runtime_phases.py
uvm/base/uvm_scheduler.py
uvm/base/uvm_scope_stack.py
uvm/base/uvm_server.py
uvm/base/uvm_spell_chkr.py
uvm/base/uvm_task_phase.py
uvm/base/uvm_topdown_phase.py
uvm/base/uvm_tr_database.py
uvm/base/uvm_tr_stream.py
uvm/base/uvm_transaction.py
uvm/base/uvm_version.py
uvm/comps/__init__.py
uvm/comps/uvm_agent.py
uvm/comps/uvm_algorithmic_comparator.py
uvm/comps/uvm_comps.py
uvm/comps/uvm_driver.py
uvm/comps/uvm_env.py
uvm/comps/uvm_in_order_comparator.py
uvm/comps/uvm_monitor.py
uvm/comps/uvm_pair.py
uvm/comps/uvm_policies.py
uvm/comps/uvm_push_driver.py
uvm/comps/uvm_random_stimulus.py
uvm/comps/uvm_scoreboard.py
uvm/comps/uvm_subscriber.py
uvm/comps/uvm_test.py
uvm/dap/__init__.py
uvm/dap/uvm_dap.py
uvm/dap/uvm_get_to_lock_dap.py
uvm/dap/uvm_set_before_get_dap.py
uvm/dap/uvm_set_get_dap_base.py
uvm/dap/uvm_simple_lock_dap.py
uvm/dpi/__init__.py
uvm_python-0.3.0.dist-info/LICENSE
uvm_python-0.3.0.dist-info/METADATA
uvm_python-0.3.0.dist-info/WHEEL
uvm_python-0.3.0.dist-info/top_level.txt
uvm_python-0.3.0.dist-info/RECORD
