Metadata-Version: 2.1
Name: uvm-python
Version: 0.3.0
Summary: uvm-python UVM implementation in Python on top of cocotb
Home-page: https://github.com/tpoikela/uvm-python
Author: Tuomas Poikela
Author-email: tuomas.sakari.poikela@gmail.com
License: Apache 2.0
Project-URL: Bug Tracker, https://github.com/tpoikela/uvm-python/issues
Keywords: UVM,SystemVerilog,Verilog,RTL,Coverage
Platform: any
Classifier: Programming Language :: Python :: 3
Classifier: License :: OSI Approved :: Apache Software License
Classifier: Topic :: Scientific/Engineering :: Electronic Design Automation (EDA)
Requires-Python: >=3.8
License-File: LICENSE
Requires-Dist: cocotb (>=1.7.2)
Requires-Dist: cocotb-bus (>=0.1.1)
Requires-Dist: cocotb-coverage (>=1.1.0)
Requires-Dist: regex (>=2019.11.1)
